flask_neo4j.py
Flask_Neo4j4-4.5.1.dist-info/LICENSE
Flask_Neo4j4-4.5.1.dist-info/METADATA
Flask_Neo4j4-4.5.1.dist-info/WHEEL
Flask_Neo4j4-4.5.1.dist-info/top_level.txt
Flask_Neo4j4-4.5.1.dist-info/RECORD
